cyperf_agent_manager/__about__.py
cyperf_agent_manager/__init__.py
cyperf_agent_manager/agent_manager.py
cyperf_agent_manager/cli.py
cyperf_agent_manager/common_constants.py
cyperf_agent_manager/common_options.py
cyperf_agent_manager/custom_types.py
cyperf_agent_manager-0.0.13.dist-info/METADATA
cyperf_agent_manager-0.0.13.dist-info/WHEEL
cyperf_agent_manager-0.0.13.dist-info/entry_points.txt
cyperf_agent_manager-0.0.13.dist-info/licenses/LICENSE
cyperf_agent_manager-0.0.13.dist-info/RECORD
