Metadata-Version: 2.1
Name: cyperf-agent-manager
Version: 0.0.13
Summary: A simple utility for executing various commands on multiple cyperf agents.
Project-URL: Documentation, https://github.com/pmajumdarKS/cyperf-agent-manager#readme.md
Project-URL: Issues, https://github.com/pmajumdarKS/cyperf-agent-manager/issues
Project-URL: Source, https://github.com/pmajumdarKS/cyperf-agent-manager
Author-email: Partha Majumdar <partha.majumdar@keysight.com>
License-Expression: MIT
License-File: LICENSE
Classifier: Development Status :: 4 - Beta
Classifier: Programming Language :: Python
Classifier: Programming Language :: Python :: 3.7
Classifier: Programming Language :: Python :: 3.8
Classifier: Programming Language :: Python :: 3.9
Classifier: Programming Language :: Python :: 3.10
Classifier: Programming Language :: Python :: 3.11
Classifier: Programming Language :: Python :: 3.12
Classifier: Programming Language :: Python :: Implementation :: CPython
Classifier: Programming Language :: Python :: Implementation :: PyPy
Requires-Python: >=3.7
Requires-Dist: click-params>=0.4.1
Requires-Dist: click>=8.0.3
Requires-Dist: paramiko>=3.3.1
Requires-Dist: scp>=0.14.5
